garf_youtube_reporting_api/__init__.py
garf_youtube_reporting_api/api_clients.py
garf_youtube_reporting_api/exceptions.py
garf_youtube_reporting_api/query_editor.py
garf_youtube_reporting_api/report_fetcher.py
garf_youtube_reporting_api-0.0.2.dist-info/METADATA
garf_youtube_reporting_api-0.0.2.dist-info/WHEEL
garf_youtube_reporting_api-0.0.2.dist-info/entry_points.txt
garf_youtube_reporting_api-0.0.2.dist-info/top_level.txt
garf_youtube_reporting_api-0.0.2.dist-info/RECORD
