Metadata-Version: 2.2
Name: garf-youtube-reporting-api
Version: 0.0.2
Author-email: "Google Inc. (gTech gPS CSE team)" <no-reply@google.com>
License: Apache 2.0
Classifier: Development Status :: 4 - Beta
Classifier: Programming Language :: Python
Requires-Python: >=3.8
Requires-Dist: garf-core
Requires-Dist: garf-io
Requires-Dist: google-api-python-client
